[
  {
    "id": 1,
    "source_user_profile_id": 1,
    "target_user_profile_id": 0,
    "source_organization_unit_id": 1,
    "target_organization_unit_id": 3,
    "office_id": 1,
    "type": "return",
    "is_accepted": false,
    "serial_number": "test 123",
    "dispatch_description": "123 test",
    "inventory_id": null,
    "created_at": "2022-02-01T00:00:00Z",
    "updated_at": "2022-02-01T00:00:00Z",
    "file_id": "21343123123"
  },
  {
    "id": 71612,
    "source_user_profile_id": 2,
    "target_user_profile_id": 1,
    "source_organization_unit_id": 6,
    "target_organization_unit_id": 2,
    "office_id": 2,
    "type": "allocation",
    "is_accepted": false,
    "serial_number": "123123",
    "dispatch_description": "test",
    "inventory_id": null,
    "created_at": "",
    "updated_at": "",
    "file_id": ""
  }
]
